asyncio_buffered_pipeline.py
asyncio_buffered_pipeline-0.0.8.dist-info/LICENSE
asyncio_buffered_pipeline-0.0.8.dist-info/METADATA
asyncio_buffered_pipeline-0.0.8.dist-info/WHEEL
asyncio_buffered_pipeline-0.0.8.dist-info/top_level.txt
asyncio_buffered_pipeline-0.0.8.dist-info/RECORD
