Metadata-Version: 2.1
Name: asyncio-buffered-pipeline
Version: 0.0.8
Summary: Parallelize pipelines of Python async iterables/generators
Home-page: https://github.com/michalc/asyncio-buffered-pipeline
Author: Michal Charemza
Author-email: michal@charemza.name
License: UNKNOWN
Platform: UNKNOWN
Classifier: Programming Language :: Python :: 3
Classifier: License :: OSI Approved :: MIT License
Classifier: Operating System :: OS Independent
Classifier: Framework :: AsyncIO
Requires-Python: >=3.7.1
